setup.py
cogwheel/__init__.py
cogwheel/__main__.py
cogwheel/compiler.py
cogwheel.egg-info/PKG-INFO
cogwheel.egg-info/SOURCES.txt
cogwheel.egg-info/dependency_links.txt
cogwheel.egg-info/top_level.txt