Metadata-Version: 1.0
Name: cogwheel
Version: 0.2.0
Summary: Wheels for everyone
Home-page: UNKNOWN
Author: UNKNOWN
Author-email: UNKNOWN
License: UNKNOWN
Platform: UNKNOWN
